[{"guest_id":1110000,"type":1,"store_id":1540000,"name":"中学女生","desc":"附近中学女生","level":1,"food_id":1130001,"coin":10,"vip_action_coin":0,"score":0,"tips_coin":10,"wait_time":25,"waitfood_time":40,"service_times_min":0,"service_times_max":0,"skin_id":1340000,"upgrade_times":50,"piece_id":0,"piece_count1":0,"piece_tips1":"0","piece_count2":0,"piece_tips2":"0","piece_count3":0,"piece_tips3":"0","taici":"爱吃甜品的女孩，运气都不会太差。","taici_diandan":"盆栽奶茶超好喝！","juqin_id":0,"icon":1590000,"maidan_taici":"请问纸巾在哪儿？"},{"guest_id":1110000,"type":1,"store_id":1540000,"name":"中学女生","desc":"邻家有女初长成","level":2,"food_id":1130001,"coin":20,"vip_action_coin":0,"score":0,"tips_coin":20,"wait_time":25,"waitfood_time":40,"service_times_min":0,"service_times_max":0,"skin_id":1340000,"upgrade_times":100,"piece_id":0,"piece_count1":0,"piece_tips1":"0","piece_count2":0,"piece_tips2":"0","piece_count3":0,"piece_tips3":"0","taici":"唯甜品与生活不可辜负！","taici_diandan":"盆栽奶茶百喝不厌~","juqin_id":0,"icon":1590000,"maidan_taici":"一定给好评！"},{"guest_id":1110000,"type":1,"store_id":1540000,"name":"中学女生","desc":"女大十八变","level":3,"food_id":1130001,"coin":30,"vip_action_coin":0,"score":0,"tips_coin":30,"wait_time":25,"waitfood_time":40,"service_times_min":0,"service_times_max":0,"skin_id":1340000,"upgrade_times":0,"piece_id":0,"piece_count1":0,"piece_tips1":"0","piece_count2":0,"piece_tips2":"0","piece_count3":0,"piece_tips3":"0","taici":"外面好像变天了。","taici_diandan":"这次换了盆栽奶茶！","juqin_id":0,"icon":1590000,"maidan_taici":"我会跟同学推荐的。"},{"guest_id":1110010,"type":1,"store_id":1540000,"name":"高中少年","desc":"少年意气奋发","level":1,"food_id":1130006,"coin":10,"vip_action_coin":0,"score":0,"tips_coin":10,"wait_time":25,"waitfood_time":40,"service_times_min":0,"service_times_max":0,"skin_id":1340010,"upgrade_times":50,"piece_id":0,"piece_count1":0,"piece_tips1":"0","piece_count2":0,"piece_tips2":"0","piece_count3":0,"piece_tips3":"0","taici":"下次想带她一起来……","taici_diandan":"手机好像快没电了。","juqin_id":0,"icon":1590010,"maidan_taici":"趁着关机之前赶快付款。"},{"guest_id":1110010,"type":1,"store_id":1540000,"name":"高中少年","desc":"学校家里两点一线","level":2,"food_id":1130006,"coin":20,"vip_action_coin":0,"score":0,"tips_coin":20,"wait_time":25,"waitfood_time":40,"service_times_min":0,"service_times_max":0,"skin_id":1340010,"upgrade_times":100,"piece_id":0,"piece_count1":0,"piece_tips1":"0","piece_count2":0,"piece_tips2":"0","piece_count3":0,"piece_tips3":"0","taici":"这里的甜品真是百吃不厌。","taici_diandan":"木糠蛋糕我挺喜欢的。","juqin_id":0,"icon":1590010,"maidan_taici":"还得回去复习。"},{"guest_id":1110010,"type":1,"store_id":1540000,"name":"高中少年","desc":"为了高考而努力","level":3,"food_id":1130006,"coin":30,"vip_action_coin":0,"score":0,"tips_coin":30,"wait_time":25,"waitfood_time":40,"service_times_min":0,"service_times_max":0,"skin_id":1340010,"upgrade_times":0,"piece_id":0,"piece_count1":0,"piece_tips1":"0","piece_count2":0,"piece_tips2":"0","piece_count3":0,"piece_tips3":"0","taici":"学校附近的甜品店真不少。","taici_diandan":"木糠蛋糕竟然这么好吃？","juqin_id":0,"icon":1590010,"maidan_taici":"吃完就有学习的动力了。"},{"guest_id":1110020,"type":1,"store_id":1540000,"name":"边缘人阿宅","desc":"社会隐形人","level":1,"food_id":1130012,"coin":10,"vip_action_coin":0,"score":0,"tips_coin":10,"wait_time":25,"waitfood_time":40,"service_times_min":0,"service_times_max":0,"skin_id":1340010,"upgrade_times":50,"piece_id":0,"piece_count1":0,"piece_tips1":"0","piece_count2":0,"piece_tips2":"0","piece_count3":0,"piece_tips3":"0","taici":"甜即正义！","taici_diandan":"这边WIFI怎么连？","juqin_id":0,"icon":1590000,"maidan_taici":"得赶快回去了。"},{"guest_id":1110020,"type":1,"store_id":1540000,"name":"边缘人阿宅","desc":"精神先行者","level":2,"food_id":1130013,"coin":20,"vip_action_coin":0,"score":0,"tips_coin":20,"wait_time":25,"waitfood_time":40,"service_times_min":0,"service_times_max":0,"skin_id":1340010,"upgrade_times":100,"piece_id":0,"piece_count1":0,"piece_tips1":"0","piece_count2":0,"piece_tips2":"0","piece_count3":0,"piece_tips3":"0","taici":"甜品才是值得出门的理由。","taici_diandan":"吃完又该长肉了。","juqin_id":0,"icon":1590000,"maidan_taici":"回去做什么好呢？"},{"guest_id":1110020,"type":1,"store_id":1540000,"name":"边缘人阿宅","desc":"内心与社会格格不入","level":3,"food_id":1130013,"coin":30,"vip_action_coin":0,"score":0,"tips_coin":30,"wait_time":25,"waitfood_time":40,"service_times_min":0,"service_times_max":0,"skin_id":1340010,"upgrade_times":0,"piece_id":0,"piece_count1":0,"piece_tips1":"0","piece_count2":0,"piece_tips2":"0","piece_count3":0,"piece_tips3":"0","taici":"家里的门关了吗……","taici_diandan":"牛牛圣代真好吃","juqin_id":0,"icon":1590000,"maidan_taici":"五星好评。"},{"guest_id":1110030,"type":1,"store_id":1540000,"name":"运动员添仔","desc":"入选国家队","level":1,"food_id":1130011,"coin":10,"vip_action_coin":0,"score":0,"tips_coin":10,"wait_time":25,"waitfood_time":40,"service_times_min":0,"service_times_max":0,"skin_id":1350000,"upgrade_times":50,"piece_id":0,"piece_count1":0,"piece_tips1":"0","piece_count2":0,"piece_tips2":"0","piece_count3":0,"piece_tips3":"0","taici":"偶尔也需要补充糖点分。","taici_diandan":"这金沙流心舒芙蕾不错哎！","juqin_id":0,"icon":1590030,"maidan_taici":"过会儿再跑步。"},{"guest_id":1110030,"type":1,"store_id":1540000,"name":"运动员添仔","desc":"参加世锦赛","level":2,"food_id":1130011,"coin":20,"vip_action_coin":0,"score":0,"tips_coin":20,"wait_time":25,"waitfood_time":40,"service_times_min":0,"service_times_max":0,"skin_id":1350001,"upgrade_times":100,"piece_id":0,"piece_count1":0,"piece_tips1":"0","piece_count2":0,"piece_tips2":"0","piece_count3":0,"piece_tips3":"0","taici":"甜食可以快速补充体力。","taici_diandan":"吃完就去运动！","juqin_id":0,"icon":1590031,"maidan_taici":"心满意足了。"},{"guest_id":1110030,"type":1,"store_id":1540000,"name":"运动员添仔","desc":"夺冠奥运会","level":3,"food_id":1130011,"coin":30,"vip_action_coin":0,"score":0,"tips_coin":30,"wait_time":25,"waitfood_time":40,"service_times_min":0,"service_times_max":0,"skin_id":1350002,"upgrade_times":0,"piece_id":0,"piece_count1":0,"piece_tips1":"0","piece_count2":0,"piece_tips2":"0","piece_count3":0,"piece_tips3":"0","taici":"这里的大份管饱！","taici_diandan":"金沙流心舒芙蕾颜色很好看啊","juqin_id":0,"icon":1590032,"maidan_taici":"用过的纸巾是干垃圾。"},{"guest_id":1110040,"type":1,"store_id":1540000,"name":"网红子萱","desc":"在抖音有5万粉丝了","level":1,"food_id":1130016,"coin":10,"vip_action_coin":0,"score":0,"tips_coin":10,"wait_time":25,"waitfood_time":40,"service_times_min":0,"service_times_max":0,"skin_id":1350010,"upgrade_times":50,"piece_id":0,"piece_count1":0,"piece_tips1":"0","piece_count2":0,"piece_tips2":"0","piece_count3":0,"piece_tips3":"0","taici":"吃完才有力气减肥呀！","taici_diandan":"海盐杏子双球也不错。","juqin_id":0,"icon":1590040,"maidan_taici":"只吃这点不算罪恶吧。"},{"guest_id":1110040,"type":1,"store_id":1540000,"name":"网红子萱","desc":"在正经综艺节目做了拼盘嘉宾","level":2,"food_id":1130016,"coin":20,"vip_action_coin":0,"score":0,"tips_coin":20,"wait_time":25,"waitfood_time":40,"service_times_min":0,"service_times_max":0,"skin_id":1350011,"upgrade_times":100,"piece_id":0,"piece_count1":0,"piece_tips1":"0","piece_count2":0,"piece_tips2":"0","piece_count3":0,"piece_tips3":"0","taici":"我就摆拍，不真吃。","taici_diandan":"为海盐杏子双球疯狂打call~","juqin_id":0,"icon":1590041,"maidan_taici":"可不能被经纪人发现我来过。"},{"guest_id":1110040,"type":1,"store_id":1540000,"name":"网红子萱","desc":"去虹桥机场有人堵着要签名了","level":3,"food_id":1130016,"coin":30,"vip_action_coin":0,"score":0,"tips_coin":30,"wait_time":25,"waitfood_time":40,"service_times_min":0,"service_times_max":0,"skin_id":1350012,"upgrade_times":0,"piece_id":0,"piece_count1":0,"piece_tips1":"0","piece_count2":0,"piece_tips2":"0","piece_count3":0,"piece_tips3":"0","taici":"偶尔一天热量超标会胖吗？","taici_diandan":"海盐杏子双球如果不加糖的话就没事吧！","juqin_id":0,"icon":1590042,"maidan_taici":"总感觉有人盯着我呢……"},{"guest_id":1110050,"type":1,"store_id":1540000,"name":"甄土豪","desc":"在城中村有10栋楼哦 不是10套","level":1,"food_id":1130006,"coin":10,"vip_action_coin":0,"score":0,"tips_coin":10,"wait_time":25,"waitfood_time":40,"service_times_min":0,"service_times_max":0,"skin_id":1340010,"upgrade_times":50,"piece_id":0,"piece_count1":0,"piece_tips1":"0","piece_count2":0,"piece_tips2":"0","piece_count3":0,"piece_tips3":"0","taici":"甜品能让人心情愉悦！","taici_diandan":"这里的木糠蛋糕味道很正~","juqin_id":0,"icon":1590000,"maidan_taici":"这里WiFi网速有点慢啊……"},{"guest_id":1110050,"type":1,"store_id":1540000,"name":"甄土豪","desc":"为了节约去菜市场的时间而买了法拉利","level":2,"food_id":1130007,"coin":20,"vip_action_coin":0,"score":0,"tips_coin":20,"wait_time":25,"waitfood_time":40,"service_times_min":0,"service_times_max":0,"skin_id":1340010,"upgrade_times":100,"piece_id":0,"piece_count1":0,"piece_tips1":"0","piece_count2":0,"piece_tips2":"0","piece_count3":0,"piece_tips3":"0","taici":"是时候该投资几家甜品店了。","taici_diandan":"大份的草莓盒子正好管饱！","juqin_id":0,"icon":1590000,"maidan_taici":"小费放收银台啦！"},{"guest_id":1110050,"type":1,"store_id":1540000,"name":"甄土豪","desc":"做人呐最重要是开心","level":3,"food_id":1130008,"coin":30,"vip_action_coin":0,"score":0,"tips_coin":30,"wait_time":25,"waitfood_time":40,"service_times_min":0,"service_times_max":0,"skin_id":1340010,"upgrade_times":0,"piece_id":0,"piece_count1":0,"piece_tips1":"0","piece_count2":0,"piece_tips2":"0","piece_count3":0,"piece_tips3":"0","taici":"店外的车位太少了。","taici_diandan":"么么茶烤包似乎不够吃啊……","juqin_id":0,"icon":1590000,"maidan_taici":"实在吃不下了，下次再来！"},{"guest_id":1110060,"type":1,"store_id":1540000,"name":"铁锤姑娘","desc":"心直口快的姑娘","level":1,"food_id":1130002,"coin":30,"vip_action_coin":0,"score":0,"tips_coin":30,"wait_time":25,"waitfood_time":40,"service_times_min":0,"service_times_max":0,"skin_id":1340030,"upgrade_times":50,"piece_id":0,"piece_count1":0,"piece_tips1":"0","piece_count2":0,"piece_tips2":"0","piece_count3":0,"piece_tips3":"0","taici":"甜食会让人兴奋。","taici_diandan":"宇治抹茶奶真是我的爱了！","juqin_id":0,"icon":1590060,"maidan_taici":"其实还想吃的……"},{"guest_id":1110060,"type":1,"store_id":1540000,"name":"铁锤姑娘","desc":"心有铁锤，随时怼人","level":2,"food_id":1130002,"coin":60,"vip_action_coin":0,"score":0,"tips_coin":60,"wait_time":25,"waitfood_time":40,"service_times_min":0,"service_times_max":0,"skin_id":1340030,"upgrade_times":100,"piece_id":0,"piece_count1":0,"piece_tips1":"0","piece_count2":0,"piece_tips2":"0","piece_count3":0,"piece_tips3":"0","taici":"你如果也爱甜品，那我们就是朋友！","taici_diandan":"真好喝！","juqin_id":0,"icon":1590060,"maidan_taici":"纸巾可以在哪儿拿？"},{"guest_id":1110060,"type":1,"store_id":1540000,"name":"铁锤姑娘","desc":"在座的各位都是钉子","level":3,"food_id":1130002,"coin":90,"vip_action_coin":0,"score":0,"tips_coin":90,"wait_time":25,"waitfood_time":40,"service_times_min":0,"service_times_max":0,"skin_id":1340030,"upgrade_times":0,"piece_id":0,"piece_count1":0,"piece_tips1":"0","piece_count2":0,"piece_tips2":"0","piece_count3":0,"piece_tips3":"0","taici":"怼人神清气爽。","taici_diandan":"这次的宇治抹茶奶是三分糖。","juqin_id":0,"icon":1590060,"maidan_taici":"下回再来！"},{"guest_id":1110070,"type":1,"store_id":1540000,"name":"精神小伙","desc":"精神小伙，不请自来","level":1,"food_id":1130008,"coin":30,"vip_action_coin":0,"score":0,"tips_coin":30,"wait_time":25,"waitfood_time":40,"service_times_min":0,"service_times_max":0,"skin_id":1340040,"upgrade_times":50,"piece_id":0,"piece_count1":0,"piece_tips1":"0","piece_count2":0,"piece_tips2":"0","piece_count3":0,"piece_tips3":"0","taici":"这个店里总飘着香味。","taici_diandan":"先拍一张照再说！","juqin_id":0,"icon":1590070,"maidan_taici":"手机拍视频没电了。"},{"guest_id":1110070,"type":1,"store_id":1540000,"name":"精神小伙","desc":"随时跳起社会摇","level":2,"food_id":1130008,"coin":60,"vip_action_coin":0,"score":0,"tips_coin":60,"wait_time":25,"waitfood_time":40,"service_times_min":0,"service_times_max":0,"skin_id":1340040,"upgrade_times":100,"piece_id":0,"piece_count1":0,"piece_tips1":"0","piece_count2":0,"piece_tips2":"0","piece_count3":0,"piece_tips3":"0","taici":"今天还有什么事来着……","taici_diandan":"不知道网红么么茶烤包味道怎么样……","juqin_id":0,"icon":1590070,"maidan_taici":"双手点赞！"},{"guest_id":1110070,"type":1,"store_id":1540000,"name":"精神小伙","desc":"精神小伙拍摄官方写真","level":3,"food_id":1130008,"coin":90,"vip_action_coin":0,"score":0,"tips_coin":90,"wait_time":25,"waitfood_time":40,"service_times_min":0,"service_times_max":0,"skin_id":1340040,"upgrade_times":0,"piece_id":0,"piece_count1":0,"piece_tips1":"0","piece_count2":0,"piece_tips2":"0","piece_count3":0,"piece_tips3":"0","taici":"跳社会摇可不容易。","taici_diandan":"我看刚刚那人点的么么茶烤包不错。","juqin_id":0,"icon":1590070,"maidan_taici":"吃得很开心。"},{"guest_id":1119999,"type":1,"store_id":1540000,"name":"中学女生","desc":"中学少女","level":1,"food_id":1130000,"coin":10,"vip_action_coin":0,"score":0,"tips_coin":10,"wait_time":900,"waitfood_time":900,"service_times_min":0,"service_times_max":0,"skin_id":1340000,"upgrade_times":0,"piece_id":0,"piece_count1":0,"piece_tips1":"0","piece_count2":0,"piece_tips2":"0","piece_count3":0,"piece_tips3":"0","taici":"班里的同学也常来这里。","taici_diandan":"我也想试试奶酪奶绿。","juqin_id":0,"icon":1590000,"maidan_taici":"这家店的甜品都很不错。"},{"guest_id":1119998,"type":1,"store_id":1540000,"name":"高中少年","desc":"高一少年","level":1,"food_id":1130006,"coin":30,"vip_action_coin":0,"score":0,"tips_coin":30,"wait_time":900,"waitfood_time":900,"service_times_min":0,"service_times_max":0,"skin_id":1340010,"upgrade_times":0,"piece_id":0,"piece_count1":0,"piece_tips1":"0","piece_count2":0,"piece_tips2":"0","piece_count3":0,"piece_tips3":"0","taici":"每次来生意都很好啊。","taici_diandan":"看起来就好好吃！","juqin_id":0,"icon":1590000,"maidan_taici":"这家店离学校很近。"},{"guest_id":1120030,"type":2,"store_id":1540000,"name":"哪吒","desc":"天降魔丸，到处作恶","level":1,"food_id":1130007,"coin":50,"vip_action_coin":1,"score":1,"tips_coin":50,"wait_time":25,"waitfood_time":40,"service_times_min":0,"service_times_max":1,"skin_id":1340010,"upgrade_times":25,"piece_id":0,"piece_count1":0,"piece_tips1":"0","piece_count2":0,"piece_tips2":"0","piece_count3":0,"piece_tips3":"0","taici":"这家甜品可是经过小爷认证的。","taici_diandan":"草莓盒子看起来不错。 ","juqin_id":1570000,"icon":1600030,"maidan_taici":"这家的甜品小爷很喜欢！"},{"guest_id":1120030,"type":2,"store_id":1540000,"name":"哪吒","desc":"大闹东海，结识好友","level":2,"food_id":1130007,"coin":100,"vip_action_coin":1,"score":1,"tips_coin":100,"wait_time":25,"waitfood_time":40,"service_times_min":0,"service_times_max":1,"skin_id":1340010,"upgrade_times":50,"piece_id":0,"piece_count1":0,"piece_tips1":"0","piece_count2":0,"piece_tips2":"0","piece_count3":0,"piece_tips3":"0","taici":"来来回回千百遍，小爷从来不疲倦。","taici_diandan":"风火轮得收起来。","juqin_id":1570001,"icon":1600031,"maidan_taici":"吃完，打道回府。"},{"guest_id":1120030,"type":2,"store_id":1540000,"name":"哪吒","desc":"自古英雄出少年","level":3,"food_id":1130007,"coin":150,"vip_action_coin":1,"score":1,"tips_coin":150,"wait_time":25,"waitfood_time":40,"service_times_min":0,"service_times_max":1,"skin_id":1340010,"upgrade_times":150,"piece_id":0,"piece_count1":0,"piece_tips1":"0","piece_count2":0,"piece_tips2":"0","piece_count3":0,"piece_tips3":"0","taici":"那群傻瓜，小爷懒得搭理。","taici_diandan":"味道好极了，我喜欢！","juqin_id":1570002,"icon":1600032,"maidan_taici":"嗝~"},{"guest_id":1120030,"type":2,"store_id":1540000,"name":"哪吒","desc":"逆天改命，重写人生","level":4,"food_id":1130007,"coin":200,"vip_action_coin":1,"score":1,"tips_coin":200,"wait_time":25,"waitfood_time":40,"service_times_min":0,"service_times_max":1,"skin_id":1340010,"upgrade_times":0,"piece_id":0,"piece_count1":0,"piece_tips1":"0","piece_count2":0,"piece_tips2":"0","piece_count3":0,"piece_tips3":"0","taici":"回去踢毽子。","taici_diandan":"简直发现宝了！","juqin_id":1570003,"icon":1600033,"maidan_taici":"小爷非常满意！"},{"guest_id":1120040,"type":2,"store_id":1540000,"name":"敖丙","desc":"灵珠转世，天才少年","level":1,"food_id":1130012,"coin":50,"vip_action_coin":10,"score":1,"tips_coin":50,"wait_time":25,"waitfood_time":40,"service_times_min":0,"service_times_max":1,"skin_id":1340010,"upgrade_times":25,"piece_id":0,"piece_count1":0,"piece_tips1":"0","piece_count2":0,"piece_tips2":"0","piece_count3":0,"piece_tips3":"0","taici":"我的背后还有整个家族。","taici_diandan":"FROGGY在龙宫没见过。","juqin_id":1570004,"icon":1600040,"maidan_taici":"得回龙宫了。"},{"guest_id":1120040,"type":2,"store_id":1540000,"name":"敖丙","desc":"东海三太子","level":2,"food_id":1130012,"coin":100,"vip_action_coin":20,"score":1,"tips_coin":100,"wait_time":25,"waitfood_time":40,"service_times_min":0,"service_times_max":1,"skin_id":1340010,"upgrade_times":50,"piece_id":0,"piece_count1":0,"piece_tips1":"0","piece_count2":0,"piece_tips2":"0","piece_count3":0,"piece_tips3":"0","taici":"甜品是什么？","taici_diandan":"外面的世界果然热闹……","juqin_id":1570005,"icon":1600041,"maidan_taici":"一会儿去陈塘关一趟吧。"},{"guest_id":1120040,"type":2,"store_id":1540000,"name":"敖丙","desc":"家族使命重于泰山","level":3,"food_id":1130012,"coin":150,"vip_action_coin":30,"score":1,"tips_coin":150,"wait_time":25,"waitfood_time":40,"service_times_min":0,"service_times_max":1,"skin_id":1340010,"upgrade_times":150,"piece_id":0,"piece_count1":0,"piece_tips1":"0","piece_count2":0,"piece_tips2":"0","piece_count3":0,"piece_tips3":"0","taici":"总觉得有什么地方怪怪的。","taici_diandan":"等会儿还想再外带一份。","juqin_id":1570006,"icon":1600042,"maidan_taici":"我还有要事，得先走一步。"},{"guest_id":1120040,"type":2,"store_id":1540000,"name":"敖丙","desc":"我命由我不由天","level":4,"food_id":1130012,"coin":200,"vip_action_coin":40,"score":1,"tips_coin":200,"wait_time":25,"waitfood_time":40,"service_times_min":0,"service_times_max":1,"skin_id":1340010,"upgrade_times":0,"piece_id":0,"piece_count1":0,"piece_tips1":"0","piece_count2":0,"piece_tips2":"0","piece_count3":0,"piece_tips3":"0","taici":"修行还得继续。","taici_diandan":"FROGGY的做法应该不简单吧？","juqin_id":1570007,"icon":1600043,"maidan_taici":"修炼不能停。"},{"guest_id":1120050,"type":2,"store_id":1540000,"name":"紫霞仙子","desc":"如来佛祖座前灯芯","level":1,"food_id":1130013,"coin":50,"vip_action_coin":10,"score":1,"tips_coin":50,"wait_time":25,"waitfood_time":40,"service_times_min":0,"service_times_max":1,"skin_id":1350050,"upgrade_times":25,"piece_id":0,"piece_count1":0,"piece_tips1":"0","piece_count2":0,"piece_tips2":"0","piece_count3":0,"piece_tips3":"0","taici":"我的意中人应该也爱吃甜品！","taici_diandan":"我的意中人也许会在这里出现……","juqin_id":1570008,"icon":1600050,"maidan_taici":"他能陪我一起吃就好了。"},{"guest_id":1120050,"type":2,"store_id":1540000,"name":"紫霞仙子","desc":"为寻真爱私自下凡","level":2,"food_id":1130013,"coin":100,"vip_action_coin":20,"score":1,"tips_coin":100,"wait_time":25,"waitfood_time":40,"service_times_min":0,"service_times_max":1,"skin_id":1350051,"upgrade_times":50,"piece_id":0,"piece_count1":0,"piece_tips1":"0","piece_count2":0,"piece_tips2":"0","piece_count3":0,"piece_tips3":"0","taici":"缘分嘛，上天安排的最大咯~","taici_diandan":"这回尝尝牛牛圣代。","juqin_id":1570009,"icon":1600051,"maidan_taici":"最近总见不到他呀……"},{"guest_id":1120050,"type":2,"store_id":1540000,"name":"紫霞仙子","desc":"只羡鸳鸯不羡仙","level":3,"food_id":1130013,"coin":150,"vip_action_coin":30,"score":1,"tips_coin":150,"wait_time":25,"waitfood_time":40,"service_times_min":0,"service_times_max":1,"skin_id":1340000,"upgrade_times":150,"piece_id":0,"piece_count1":0,"piece_tips1":"0","piece_count2":0,"piece_tips2":"0","piece_count3":0,"piece_tips3":"0","taici":"我们大家立刻开始这段感情吧！","taici_diandan":"差点掉地上了。","juqin_id":1570010,"icon":1600052,"maidan_taici":"我的月光宝盒呢？"},{"guest_id":1120050,"type":2,"store_id":1540000,"name":"紫霞仙子","desc":"为爱痴狂的单纯仙子","level":4,"food_id":1130013,"coin":200,"vip_action_coin":40,"score":1,"tips_coin":200,"wait_time":25,"waitfood_time":40,"service_times_min":0,"service_times_max":1,"skin_id":1340000,"upgrade_times":0,"piece_id":0,"piece_count1":0,"piece_tips1":"0","piece_count2":0,"piece_tips2":"0","piece_count3":0,"piece_tips3":"0","taici":"那个男人长得好像他……","taici_diandan":"好喜欢牛牛圣代吖。","juqin_id":1570011,"icon":1600053,"maidan_taici":"我好像看到一个可疑的人。"},{"guest_id":1120060,"type":2,"store_id":1540000,"name":"周星仔","desc":"原本是爱自嘲的龙套演员","level":1,"food_id":1130018,"coin":50,"vip_action_coin":10,"score":1,"tips_coin":50,"wait_time":25,"waitfood_time":40,"service_times_min":0,"service_times_max":1,"skin_id":1350060,"upgrade_times":25,"piece_id":0,"piece_count1":0,"piece_tips1":"0","piece_count2":0,"piece_tips2":"0","piece_count3":0,"piece_tips3":"0","taici":"人世间最痛苦的事莫过于错过这家店。","taici_diandan":"跟着别人点了热带百香绿。","juqin_id":1570012,"icon":1600060,"maidan_taici":"我是老顾客，下次记得优惠点。"},{"guest_id":1120060,"type":2,"store_id":1540000,"name":"周星仔","desc":"不经意自导自演，电影大热","level":2,"food_id":1130018,"coin":100,"vip_action_coin":20,"score":1,"tips_coin":100,"wait_time":25,"waitfood_time":40,"service_times_min":0,"service_times_max":1,"skin_id":1350061,"upgrade_times":50,"piece_id":0,"piece_count1":0,"piece_tips1":"0","piece_count2":0,"piece_tips2":"0","piece_count3":0,"piece_tips3":"0","taici":"曾经有一份真诚的爱情放在我面前…….","taici_diandan":"帅哥也是要吃东西的嘛！","juqin_id":1570013,"icon":1600061,"maidan_taici":"导演找我有点事，先走了。"},{"guest_id":1120060,"type":2,"store_id":1540000,"name":"周星仔","desc":"巅峰时退居幕后成著名导演","level":3,"food_id":1130018,"coin":150,"vip_action_coin":30,"score":1,"tips_coin":150,"wait_time":25,"waitfood_time":40,"service_times_min":0,"service_times_max":1,"skin_id":1340010,"upgrade_times":150,"piece_id":0,"piece_count1":0,"piece_tips1":"0","piece_count2":0,"piece_tips2":"0","piece_count3":0,"piece_tips3":"0","taici":"眼睛进沙子了，请给我一包纸巾。","taici_diandan":"差点把我热带百香绿掉了！","juqin_id":1570014,"icon":1600062,"maidan_taici":"刚才我把剧本放哪儿了？"},{"guest_id":1120060,"type":2,"store_id":1540000,"name":"周星仔","desc":"他的内心：不会演戏的导演不是好编剧","level":4,"food_id":1130018,"coin":200,"vip_action_coin":40,"score":1,"tips_coin":200,"wait_time":25,"waitfood_time":40,"service_times_min":0,"service_times_max":1,"skin_id":1340010,"upgrade_times":0,"piece_id":0,"piece_count1":0,"piece_tips1":"0","piece_count2":0,"piece_tips2":"0","piece_count3":0,"piece_tips3":"0","taici":"最近在构思一个电影剧本……","taici_diandan":"吃个东西就不要盯着我看了。","juqin_id":1570015,"icon":1600063,"maidan_taici":"我得去片场了。"},{"guest_id":1120070,"type":2,"store_id":1540000,"name":"小龙女","desc":"东海龙王小女儿","level":1,"food_id":1130019,"coin":50,"vip_action_coin":10,"score":1,"tips_coin":50,"wait_time":25,"waitfood_time":40,"service_times_min":0,"service_times_max":1,"skin_id":1340000,"upgrade_times":50,"piece_id":0,"piece_count1":0,"piece_tips1":"0","piece_count2":0,"piece_tips2":"0","piece_count3":0,"piece_tips3":"0","taici":"只要吹响海螺，我就能听到。","taici_diandan":"在海里没尝过的味道。","juqin_id":1570016,"icon":1600070,"maidan_taici":"不能离开东海太久……"},{"guest_id":1120070,"type":2,"store_id":1540000,"name":"小龙女","desc":"古灵精怪的龙公主","level":2,"food_id":1130019,"coin":100,"vip_action_coin":20,"score":1,"tips_coin":100,"wait_time":25,"waitfood_time":40,"service_times_min":0,"service_times_max":1,"skin_id":1340000,"upgrade_times":150,"piece_id":0,"piece_count1":0,"piece_tips1":"0","piece_count2":0,"piece_tips2":"0","piece_count3":0,"piece_tips3":"0","taici":"外面的世界好有趣啊！","taici_diandan":"我想念青露乃姬的味道很久了。","juqin_id":1570017,"icon":1600071,"maidan_taici":"刚才差点露处原形。"},{"guest_id":1120070,"type":2,"store_id":1540000,"name":"小龙女","desc":"是非分明，仗义人间","level":3,"food_id":1130019,"coin":150,"vip_action_coin":30,"score":1,"tips_coin":150,"wait_time":25,"waitfood_time":40,"service_times_min":0,"service_times_max":1,"skin_id":1340000,"upgrade_times":300,"piece_id":0,"piece_count1":0,"piece_tips1":"0","piece_count2":0,"piece_tips2":"0","piece_count3":0,"piece_tips3":"0","taici":"龙宫好像没有甜品呢……","taici_diandan":"早知道就多点一份了。","juqin_id":1570018,"icon":1600072,"maidan_taici":"下次还来！"},{"guest_id":1120070,"type":2,"store_id":1540000,"name":"小龙女","desc":"为救东海化为泉眼","level":4,"food_id":1130019,"coin":200,"vip_action_coin":40,"score":1,"tips_coin":200,"wait_time":25,"waitfood_time":40,"service_times_min":0,"service_times_max":1,"skin_id":1340000,"upgrade_times":0,"piece_id":0,"piece_count1":0,"piece_tips1":"0","piece_count2":0,"piece_tips2":"0","piece_count3":0,"piece_tips3":"0","taici":"不要污染大海哦~","taici_diandan":"迫不及待想尝尝青露乃姬了。","juqin_id":1570019,"icon":1600073,"maidan_taici":"小费放在收银台是吧？"},{"guest_id":1120080,"type":2,"store_id":1540000,"name":"悟空","desc":"本体是来自外星的赛亚人","level":1,"food_id":1130003,"coin":50,"vip_action_coin":10,"score":1,"tips_coin":50,"wait_time":25,"waitfood_time":40,"service_times_min":0,"service_times_max":1,"skin_id":1340010,"upgrade_times":50,"piece_id":0,"piece_count1":0,"piece_tips1":"0","piece_count2":0,"piece_tips2":"0","piece_count3":0,"piece_tips3":"0","taici":"筋斗云不知道去哪儿了。","taici_diandan":"桃桃乌龙奶盖的量有些少啊……","juqin_id":1570020,"icon":1600080,"maidan_taici":"我如意棒放哪儿了？"},{"guest_id":1120080,"type":2,"store_id":1540000,"name":"悟空","desc":"想当年初出茅庐，不谙世事","level":2,"food_id":1130003,"coin":100,"vip_action_coin":20,"score":1,"tips_coin":100,"wait_time":25,"waitfood_time":40,"service_times_min":0,"service_times_max":1,"skin_id":1340010,"upgrade_times":150,"piece_id":0,"piece_count1":0,"piece_tips1":"0","piece_count2":0,"piece_tips2":"0","piece_count3":0,"piece_tips3":"0","taici":"好饿啊。","taici_diandan":"桃桃乌龙奶盖应该会吃不饱吧。","juqin_id":1570021,"icon":1600081,"maidan_taici":"还没吃饱……"},{"guest_id":1120080,"type":2,"store_id":1540000,"name":"悟空","desc":"终生都在追求武道极限的修行狂人","level":3,"food_id":1130003,"coin":150,"vip_action_coin":30,"score":1,"tips_coin":150,"wait_time":25,"waitfood_time":40,"service_times_min":0,"service_times_max":1,"skin_id":1340010,"upgrade_times":300,"piece_id":0,"piece_count1":0,"piece_tips1":"0","piece_count2":0,"piece_tips2":"0","piece_count3":0,"piece_tips3":"0","taici":"今天的修行还没结束。","taici_diandan":"待会儿带些回去给琪琪吃。","juqin_id":1570022,"icon":1600082,"maidan_taici":"不早点回去，琪琪会担心。"},{"guest_id":1120080,"type":2,"store_id":1540000,"name":"悟空","desc":"无意中成为拯救地球的超级英雄","level":4,"food_id":1130003,"coin":200,"vip_action_coin":40,"score":1,"tips_coin":200,"wait_time":25,"waitfood_time":40,"service_times_min":0,"service_times_max":1,"skin_id":1340010,"upgrade_times":0,"piece_id":0,"piece_count1":0,"piece_tips1":"0","piece_count2":0,"piece_tips2":"0","piece_count3":0,"piece_tips3":"0","taici":"该怎么解释赛亚人呢……","taici_diandan":"吃东西的时候请勿打扰。","juqin_id":1570023,"icon":1600083,"maidan_taici":"今天的修行还没结束。"},{"guest_id":1120090,"type":2,"store_id":1540000,"name":"吴承恩","desc":"一位过目成诵的天才","level":1,"food_id":1130009,"coin":50,"vip_action_coin":10,"score":1,"tips_coin":50,"wait_time":25,"waitfood_time":40,"service_times_min":0,"service_times_max":1,"skin_id":1340010,"upgrade_times":50,"piece_id":0,"piece_count1":0,"piece_tips1":"0","piece_count2":0,"piece_tips2":"0","piece_count3":0,"piece_tips3":"0","taici":"吾乃淮才士也。","taici_diandan":"杯子熔岩蛋糕乃吾之所爱。","juqin_id":1570024,"icon":1600090,"maidan_taici":"回去继续著书。"},{"guest_id":1120090,"type":2,"store_id":1540000,"name":"吴承恩","desc":"精于绘画 擅长书法","level":2,"food_id":1130009,"coin":100,"vip_action_coin":20,"score":1,"tips_coin":100,"wait_time":25,"waitfood_time":40,"service_times_min":0,"service_times_max":1,"skin_id":1340010,"upgrade_times":150,"piece_id":0,"piece_count1":0,"piece_tips1":"0","piece_count2":0,"piece_tips2":"0","piece_count3":0,"piece_tips3":"0","taici":"敏而好学，博览群书。","taici_diandan":"吾愿为杯子熔岩蛋糕作文一篇。","juqin_id":1570025,"icon":1600091,"maidan_taici":"今日亦有些感悟……"},{"guest_id":1120090,"type":2,"store_id":1540000,"name":"吴承恩","desc":"撰写志怪小说来表达对官场的不满和愤懑","level":3,"food_id":1130009,"coin":150,"vip_action_coin":30,"score":1,"tips_coin":150,"wait_time":25,"waitfood_time":40,"service_times_min":0,"service_times_max":1,"skin_id":1340010,"upgrade_times":300,"piece_id":0,"piece_count1":0,"piece_tips1":"0","piece_count2":0,"piece_tips2":"0","piece_count3":0,"piece_tips3":"0","taici":"不如就叫《西游记》吧……","taici_diandan":"这里的食物真美味。","juqin_id":1570026,"icon":1600092,"maidan_taici":"吾甚是满意。"},{"guest_id":1120090,"type":2,"store_id":1540000,"name":"吴承恩","desc":"影响了一大批小朋友暑假生活的明代小说家","level":4,"food_id":1130009,"coin":200,"vip_action_coin":40,"score":1,"tips_coin":200,"wait_time":25,"waitfood_time":40,"service_times_min":0,"service_times_max":1,"skin_id":1340010,"upgrade_times":0,"piece_id":0,"piece_count1":0,"piece_tips1":"0","piece_count2":0,"piece_tips2":"0","piece_count3":0,"piece_tips3":"0","taici":"写文是一种乐趣。","taici_diandan":"有些迫不及待想品尝杯子熔岩蛋糕了。","juqin_id":1570027,"icon":1600093,"maidan_taici":"今日一别……明日再来！"},{"guest_id":1120100,"type":2,"store_id":1540000,"name":"孙行者","desc":"石猴出世，占山为王","level":1,"food_id":1130014,"coin":50,"vip_action_coin":10,"score":1,"tips_coin":50,"wait_time":25,"waitfood_time":40,"service_times_min":0,"service_times_max":1,"skin_id":1340010,"upgrade_times":50,"piece_id":0,"piece_count1":0,"piece_tips1":"0","piece_count2":0,"piece_tips2":"0","piece_count3":0,"piece_tips3":"0","taici":"俺老孙到此一游。","taici_diandan":"来一份巧克力雪山尝尝鲜。","juqin_id":1570028,"icon":1600100,"maidan_taici":"这里的甜品比蟠桃好吃多了！"},{"guest_id":1120100,"type":2,"store_id":1540000,"name":"孙行者","desc":"齐天大圣大闹天宫","level":2,"food_id":1130014,"coin":100,"vip_action_coin":20,"score":1,"tips_coin":100,"wait_time":25,"waitfood_time":40,"service_times_min":0,"service_times_max":1,"skin_id":1340010,"upgrade_times":150,"piece_id":0,"piece_count1":0,"piece_tips1":"0","piece_count2":0,"piece_tips2":"0","piece_count3":0,"piece_tips3":"0","taici":"俺乃齐天大圣美猴王。","taici_diandan":"味道比蟠桃好多了。","juqin_id":1570029,"icon":1600101,"maidan_taici":"带回去给猴子猴孙们吃……"},{"guest_id":1120100,"type":2,"store_id":1540000,"name":"孙行者","desc":"护送唐僧西天取经","level":3,"food_id":1130014,"coin":150,"vip_action_coin":30,"score":1,"tips_coin":150,"wait_time":25,"waitfood_time":40,"service_times_min":0,"service_times_max":1,"skin_id":1340010,"upgrade_times":300,"piece_id":0,"piece_count1":0,"piece_tips1":"0","piece_count2":0,"piece_tips2":"0","piece_count3":0,"piece_tips3":"0","taici":"我大闹天宫的时候你们还没出生呢！","taici_diandan":"法术也变不出巧克力雪山的味道。","juqin_id":1570030,"icon":1600102,"maidan_taici":"俺老孙去也！"},{"guest_id":1120100,"type":2,"store_id":1540000,"name":"孙行者","desc":"历经八十一难，终成斗战胜佛","level":4,"food_id":1130014,"coin":200,"vip_action_coin":40,"score":1,"tips_coin":200,"wait_time":25,"waitfood_time":40,"service_times_min":0,"service_times_max":1,"skin_id":1340010,"upgrade_times":0,"piece_id":0,"piece_count1":0,"piece_tips1":"0","piece_count2":0,"piece_tips2":"0","piece_count3":0,"piece_tips3":"0","taici":"一走就是几万里。","taici_diandan":"老孙的巧克力雪山！","juqin_id":1570031,"icon":1600103,"maidan_taici":"老孙到此一游。"},{"guest_id":1120110,"type":2,"store_id":1540000,"name":"李白","desc":"早年天才，喜好剑术","level":1,"food_id":1130015,"coin":50,"vip_action_coin":10,"score":1,"tips_coin":50,"wait_time":25,"waitfood_time":40,"service_times_min":0,"service_times_max":1,"skin_id":1340010,"upgrade_times":100,"piece_id":0,"piece_count1":0,"piece_tips1":"0","piece_count2":0,"piece_tips2":"0","piece_count3":0,"piece_tips3":"0","taici":"乘风破浪会有时，直挂云帆济沧海。","taici_diandan":"今夕何夕？","juqin_id":1570032,"icon":1600110,"maidan_taici":"举杯邀明月……哎？天还没黑。"},{"guest_id":1120110,"type":2,"store_id":1540000,"name":"李白","desc":"仗剑去国，辞亲远游","level":2,"food_id":1130015,"coin":100,"vip_action_coin":20,"score":1,"tips_coin":100,"wait_time":25,"waitfood_time":40,"service_times_min":0,"service_times_max":1,"skin_id":1340010,"upgrade_times":200,"piece_id":0,"piece_count1":0,"piece_tips1":"0","piece_count2":0,"piece_tips2":"0","piece_count3":0,"piece_tips3":"0","taici":"云想衣裳花想容……","taici_diandan":"黑糖虎纹冰的味道抵得上美酒。","juqin_id":1570033,"icon":1600111,"maidan_taici":"今朝有甜品，明日还复来。"},{"guest_id":1120110,"type":2,"store_id":1540000,"name":"李白","desc":"献赋谋仕获“谪仙人”称号","level":3,"food_id":1130015,"coin":150,"vip_action_coin":30,"score":1,"tips_coin":150,"wait_time":25,"waitfood_time":40,"service_times_min":0,"service_times_max":1,"skin_id":1340010,"upgrade_times":500,"piece_id":0,"piece_count1":0,"piece_tips1":"0","piece_count2":0,"piece_tips2":"0","piece_count3":0,"piece_tips3":"0","taici":"为此处赋诗一首吧。","taici_diandan":"一斗酒，一份黑糖虎纹冰，美哉。","juqin_id":1570034,"icon":1600112,"maidan_taici":"必须打赏！"},{"guest_id":1120110,"type":2,"store_id":1540000,"name":"李白","desc":"人称诗仙的“酒仙”","level":4,"food_id":1130015,"coin":200,"vip_action_coin":40,"score":1,"tips_coin":200,"wait_time":25,"waitfood_time":40,"service_times_min":0,"service_times_max":1,"skin_id":1340010,"upgrade_times":0,"piece_id":0,"piece_count1":0,"piece_tips1":"0","piece_count2":0,"piece_tips2":"0","piece_count3":0,"piece_tips3":"0","taici":"我怕是喝醉了。","taici_diandan":"黑糖虎纹冰的美味，值得赋诗一首。","juqin_id":1570035,"icon":1600113,"maidan_taici":"下次记得留个座儿。"},{"guest_id":1120120,"type":2,"store_id":1540000,"name":"李靖","desc":"爱民如子的陈塘关镇关总兵","level":1,"food_id":1130020,"coin":150,"vip_action_coin":30,"score":1,"tips_coin":150,"wait_time":25,"waitfood_time":40,"service_times_min":0,"service_times_max":1,"skin_id":1340010,"upgrade_times":100,"piece_id":0,"piece_count1":0,"piece_tips1":"0","piece_count2":0,"piece_tips2":"0","piece_count3":0,"piece_tips3":"0","taici":"陈塘关的百姓应该也会喜欢……","taici_diandan":"李某的覆盆子乌龙请快些，还要带给夫人。","juqin_id":1570036,"icon":1600120,"maidan_taici":"现在就回陈塘关。"},{"guest_id":1120120,"type":2,"store_id":1540000,"name":"李靖","desc":"镇关总兵飞升仙班","level":2,"food_id":1130020,"coin":300,"vip_action_coin":60,"score":1,"tips_coin":300,"wait_time":25,"waitfood_time":40,"service_times_min":0,"service_times_max":1,"skin_id":1340010,"upgrade_times":200,"piece_id":0,"piece_count1":0,"piece_tips1":"0","piece_count2":0,"piece_tips2":"0","piece_count3":0,"piece_tips3":"0","taici":"夫人甚是喜欢这里的甜食。","taici_diandan":"吃完给吒儿捎一份。\"","juqin_id":1570037,"icon":1600121,"maidan_taici":"打包带走的在哪儿取？"},{"guest_id":1120120,"type":2,"store_id":1540000,"name":"李靖","desc":"得燃灯道人指点 赐予玲珑黄金塔","level":3,"food_id":1130020,"coin":450,"vip_action_coin":90,"score":1,"tips_coin":450,"wait_time":25,"waitfood_time":40,"service_times_min":0,"service_times_max":1,"skin_id":1340010,"upgrade_times":500,"piece_id":0,"piece_count1":0,"piece_tips1":"0","piece_count2":0,"piece_tips2":"0","piece_count3":0,"piece_tips3":"0","taici":"哪吒最近常提起这家店。","taici_diandan":"吒儿似乎也喜欢覆盆子乌龙。","juqin_id":1570038,"icon":1600122,"maidan_taici":"夫人应该等急了。"},{"guest_id":1120120,"type":2,"store_id":1540000,"name":"李靖","desc":"掌管十万天兵天将的托塔天王","level":4,"food_id":1130020,"coin":600,"vip_action_coin":120,"score":1,"tips_coin":600,"wait_time":25,"waitfood_time":40,"service_times_min":0,"service_times_max":1,"skin_id":1340010,"upgrade_times":0,"piece_id":0,"piece_count1":0,"piece_tips1":"0","piece_count2":0,"piece_tips2":"0","piece_count3":0,"piece_tips3":"0","taici":"哪吒这孩子真不让人省心。","taici_diandan":"下次继续点覆盆子乌龙。","juqin_id":1570039,"icon":1600123,"maidan_taici":"李某下次再来。"},{"guest_id":1120130,"type":2,"store_id":1540000,"name":"李龙浩","desc":"无名音乐制作人","level":1,"food_id":1130021,"coin":150,"vip_action_coin":30,"score":1,"tips_coin":150,"wait_time":25,"waitfood_time":40,"service_times_min":0,"service_times_max":1,"skin_id":1340010,"upgrade_times":100,"piece_id":0,"piece_count1":0,"piece_tips1":"0","piece_count2":0,"piece_tips2":"0","piece_count3":0,"piece_tips3":"0","taici":"如果能重来我要学李白。","taici_diandan":"猕恋青果速度还挺快。","juqin_id":1570040,"icon":1600130,"maidan_taici":"甜品真是我的灵感源泉。"},{"guest_id":1120130,"type":2,"store_id":1540000,"name":"李龙浩","desc":"新人歌手一曲成名","level":2,"food_id":1130021,"coin":300,"vip_action_coin":60,"score":1,"tips_coin":300,"wait_time":25,"waitfood_time":40,"service_times_min":0,"service_times_max":1,"skin_id":1340010,"upgrade_times":200,"piece_id":0,"piece_count1":0,"piece_tips1":"0","piece_count2":0,"piece_tips2":"0","piece_count3":0,"piece_tips3":"0","taici":"别盯着我，眼睛小但看得清。","taici_diandan":"锁定猕恋青果。","juqin_id":1570041,"icon":1600131,"maidan_taici":"刚才的灵感得立马回去记下来。"},{"guest_id":1120130,"type":2,"store_id":1540000,"name":"李龙浩","desc":"实实在在的全能音乐人","level":3,"food_id":1130021,"coin":450,"vip_action_coin":90,"score":1,"tips_coin":450,"wait_time":25,"waitfood_time":40,"service_times_min":0,"service_times_max":1,"skin_id":1340010,"upgrade_times":500,"piece_id":0,"piece_count1":0,"piece_tips1":"0","piece_count2":0,"piece_tips2":"0","piece_count3":0,"piece_tips3":"0","taici":"刚刚又有人说我眼睛小。","taici_diandan":"这里的WiFi密码是什么？","juqin_id":1570042,"icon":1600132,"maidan_taici":"我一直很喜欢这里的甜品。"},{"guest_id":1120130,"type":2,"store_id":1540000,"name":"李龙浩","desc":"一个被演唱事业耽误的段子手","level":4,"food_id":1130021,"coin":600,"vip_action_coin":120,"score":1,"tips_coin":600,"wait_time":25,"waitfood_time":40,"service_times_min":0,"service_times_max":1,"skin_id":1340010,"upgrade_times":0,"piece_id":0,"piece_count1":0,"piece_tips1":"0","piece_count2":0,"piece_tips2":"0","piece_count3":0,"piece_tips3":"0","taici":"我很严肃吗？","taici_diandan":"老婆昨天点的是猕恋青果吧……","juqin_id":1570043,"icon":1600133,"maidan_taici":"互相折磨到白头……♫"},{"guest_id":1120140,"type":2,"store_id":1540000,"name":"太白刺客","desc":"长安城仗剑书诗句","level":1,"food_id":1130004,"coin":150,"vip_action_coin":30,"score":1,"tips_coin":150,"wait_time":25,"waitfood_time":40,"service_times_min":0,"service_times_max":1,"skin_id":1340010,"upgrade_times":100,"piece_id":0,"piece_count1":0,"piece_tips1":"0","piece_count2":0,"piece_tips2":"0","piece_count3":0,"piece_tips3":"0","taici":"今朝有酒今朝醉。","taici_diandan":"牛魔王黑砖奶茶妙极了！","juqin_id":1570044,"icon":1600140,"maidan_taici":"我不困，只是眼睛有点小。"},{"guest_id":1120140,"type":2,"store_id":1540000,"name":"太白刺客","desc":"年少轻狂，试剑天下","level":2,"food_id":1130004,"coin":300,"vip_action_coin":60,"score":1,"tips_coin":300,"wait_time":25,"waitfood_time":40,"service_times_min":0,"service_times_max":1,"skin_id":1340010,"upgrade_times":200,"piece_id":0,"piece_count1":0,"piece_tips1":"0","piece_count2":0,"piece_tips2":"0","piece_count3":0,"piece_tips3":"0","taici":"你的血让我诗兴大发。","taici_diandan":"以后就牛魔王黑砖奶茶了。","juqin_id":1570045,"icon":1600141,"maidan_taici":"总体感觉不错。"},{"guest_id":1120140,"type":2,"store_id":1540000,"name":"太白刺客","desc":"十步杀一人，千里不留行","level":3,"food_id":1130004,"coin":450,"vip_action_coin":90,"score":1,"tips_coin":450,"wait_time":25,"waitfood_time":40,"service_times_min":0,"service_times_max":1,"skin_id":1340010,"upgrade_times":500,"piece_id":0,"piece_count1":0,"piece_tips1":"0","piece_count2":0,"piece_tips2":"0","piece_count3":0,"piece_tips3":"0","taici":"时间也抹杀不了颜值。","taici_diandan":"真想为它赋诗一首。","juqin_id":1570046,"icon":1600142,"maidan_taici":"吃得有点多，只想睡觉。"},{"guest_id":1120140,"type":2,"store_id":1540000,"name":"太白刺客","desc":"剑仙太白，三入长安","level":4,"food_id":1130004,"coin":600,"vip_action_coin":120,"score":1,"tips_coin":600,"wait_time":25,"waitfood_time":40,"service_times_min":0,"service_times_max":1,"skin_id":1340010,"upgrade_times":0,"piece_id":0,"piece_count1":0,"piece_tips1":"0","piece_count2":0,"piece_tips2":"0","piece_count3":0,"piece_tips3":"0","taici":"败给我不丢脸，还附赠诗哦！","taici_diandan":"速度不赖啊！","juqin_id":1570047,"icon":1600143,"maidan_taici":"门口不会都是来求败的吧？"},{"guest_id":1120150,"type":2,"store_id":1540000,"name":"太乙真人","desc":"元始天尊座下弟子","level":1,"food_id":1130005,"coin":150,"vip_action_coin":30,"score":1,"tips_coin":150,"wait_time":25,"waitfood_time":40,"service_times_min":0,"service_times_max":1,"skin_id":1340010,"upgrade_times":100,"piece_id":0,"piece_count1":0,"piece_tips1":"0","piece_count2":0,"piece_tips2":"0","piece_count3":0,"piece_tips3":"0","taici":"臭小子又给我惹祸了。","taici_diandan":"吃完再评价。","juqin_id":1570048,"icon":1600150,"maidan_taici":"右眼皮跳……哪吒会不会又闯祸了？"},{"guest_id":1120150,"type":2,"store_id":1540000,"name":"太乙真人","desc":"见识广泛，精通各类妙法","level":2,"food_id":1130005,"coin":300,"vip_action_coin":60,"score":1,"tips_coin":300,"wait_time":25,"waitfood_time":40,"service_times_min":0,"service_times_max":1,"skin_id":1340010,"upgrade_times":200,"piece_id":0,"piece_count1":0,"piece_tips1":"0","piece_count2":0,"piece_tips2":"0","piece_count3":0,"piece_tips3":"0","taici":"道生一，一生二！","taici_diandan":"乌龙爷爷看起来不错。","juqin_id":1570049,"icon":1600151,"maidan_taici":"赶快回去盯着哪吒。"},{"guest_id":1120150,"type":2,"store_id":1540000,"name":"太乙真人","desc":"喜获爱徒，断其人间因果","level":3,"food_id":1130005,"coin":450,"vip_action_coin":90,"score":1,"tips_coin":450,"wait_time":25,"waitfood_time":40,"service_times_min":0,"service_times_max":1,"skin_id":1340010,"upgrade_times":500,"piece_id":0,"piece_count1":0,"piece_tips1":"0","piece_count2":0,"piece_tips2":"0","piece_count3":0,"piece_tips3":"0","taici":"三昧真火还没教给哪吒。","taici_diandan":"真是美味！","juqin_id":1570050,"icon":1600152,"maidan_taici":"吃饱喝足。"},{"guest_id":1120150,"type":2,"store_id":1540000,"name":"太乙真人","desc":"仁慈和爱的绝世师仙","level":4,"food_id":1130005,"coin":600,"vip_action_coin":120,"score":1,"tips_coin":600,"wait_time":25,"waitfood_time":40,"service_times_min":0,"service_times_max":1,"skin_id":1340010,"upgrade_times":0,"piece_id":0,"piece_count1":0,"piece_tips1":"0","piece_count2":0,"piece_tips2":"0","piece_count3":0,"piece_tips3":"0","taici":"我可是神仙！","taici_diandan":"这种食物天上都没有！","juqin_id":1570051,"icon":1600153,"maidan_taici":"味道真不错，下次还来。"},{"guest_id":1120160,"type":2,"store_id":1540000,"name":"撒三岁","desc":"保送名校的高材生","level":1,"food_id":1130010,"coin":150,"vip_action_coin":30,"score":1,"tips_coin":150,"wait_time":25,"waitfood_time":40,"service_times_min":0,"service_times_max":1,"skin_id":1340010,"upgrade_times":100,"piece_id":0,"piece_count1":0,"piece_tips1":"0","piece_count2":0,"piece_tips2":"0","piece_count3":0,"piece_tips3":"0","taici":"只有百米短跑，才在乎起跑线。","taici_diandan":"一会儿还得开会。","juqin_id":1570052,"icon":1600160,"maidan_taici":"下次会在节目里推荐的。"},{"guest_id":1120160,"type":2,"store_id":1540000,"name":"撒三岁","desc":"自黑自嘲进击主持人","level":2,"food_id":1130010,"coin":300,"vip_action_coin":60,"score":1,"tips_coin":300,"wait_time":25,"waitfood_time":40,"service_times_min":0,"service_times_max":1,"skin_id":1340010,"upgrade_times":200,"piece_id":0,"piece_count1":0,"piece_tips1":"0","piece_count2":0,"piece_tips2":"0","piece_count3":0,"piece_tips3":"0","taici":"他们都叫我狗头侦探。","taici_diandan":"我家李白也喜欢这里的岩烧芝士蛋糕。","juqin_id":1570053,"icon":1600161,"maidan_taici":"刚才有个妹子一直盯着我。"},{"guest_id":1120160,"type":2,"store_id":1540000,"name":"撒三岁","desc":"幽默风趣晋升名主持","level":3,"food_id":1130010,"coin":450,"vip_action_coin":90,"score":1,"tips_coin":450,"wait_time":25,"waitfood_time":40,"service_times_min":0,"service_times_max":1,"skin_id":1340010,"upgrade_times":500,"piece_id":0,"piece_count1":0,"piece_tips1":"0","piece_count2":0,"piece_tips2":"0","piece_count3":0,"piece_tips3":"0","taici":"我是被迫保送的名校。","taici_diandan":"前几天参加节目吃到过岩烧芝士蛋糕。","juqin_id":1570054,"icon":1600162,"maidan_taici":"美味不需要解释。"},{"guest_id":1120160,"type":2,"store_id":1540000,"name":"撒三岁","desc":"唱功一流的芳心纵火犯","level":4,"food_id":1130010,"coin":600,"vip_action_coin":120,"score":1,"tips_coin":600,"wait_time":25,"waitfood_time":40,"service_times_min":0,"service_times_max":1,"skin_id":1340010,"upgrade_times":0,"piece_id":0,"piece_count1":0,"piece_tips1":"0","piece_count2":0,"piece_tips2":"0","piece_count3":0,"piece_tips3":"0","taici":"芳心纵火犯就是我了。","taici_diandan":"这就是嘉宾提到过的岩烧芝士蛋糕。","juqin_id":1570055,"icon":1600163,"maidan_taici":"下次还会来的！"}]